{
  "VERSION": "230605",
  "INFO": "增加搜索时过滤已删除角色\nGM工具增加金币数量编辑\n合并查寻结果时显示角色名",
  "URL": "http://101.42.224.206:8888/dnf_package_tool_sponsor_230605.zip",
  "history": {
    "230528": "在线更新版",
    "230529": "修复背包编辑窗口无效果的bug",
    "230530": "优化数据库连接方式，减少数据读写冲突",
    "230531": "增加邮件发送时发件人和邮件文本的缓存",
    "230601": "修复innoDB不执行提交操作的问题",
    "230602": "合并GM工具和背包编辑界面。",
    "230603": "修复无法加载PVF、innoDB重载角色背包无法更新数据的问题",
    "230604": "修复连接数据库后，切换其他IP时数据仍为之前数据库的bug",
    "230601b": "背包编辑窗口增加角色信息提示栏",
    "230602b": "增加简易模式,去除自定义分组",
    "230602c": "标准模式仍可以与旧版相同打开三个窗口进行操作",
    "230531b": "修复无法进行角色名查询的bug",
    "230531c": "修复连接数据库后不自动加载、无法自定义分类的bug",
    "230531a": "将契约道具归纳为消耗品",
    "230603b": "修复数据库十分钟断连需重新连接的问题",
    "230604b": "修复切换IP偶发的无法连接bug\n修正临时列表的角色ID和账号ID顺序(旧版无法正确群发和充值)\n增加邮件发送确认"
  }
}